LICENSE.rst
README.rst
setup.cfg
setup.py
galaxie_audio.egg-info/PKG-INFO
galaxie_audio.egg-info/SOURCES.txt
galaxie_audio.egg-info/dependency_links.txt
galaxie_audio.egg-info/not-zip-safe
galaxie_audio.egg-info/requires.txt
galaxie_audio.egg-info/top_level.txt
glxaudio/Audio.py
glxaudio/AudioConstants.py
glxaudio/AudioInterfaces.py
glxaudio/AudioPlayer.py
glxaudio/AudioRecorder.py
glxaudio/AudioSWHear.py
glxaudio/AudioScope.py
glxaudio/AudioSpectrogram.py
glxaudio/AudioUtils.py
glxaudio/EventBus.py
glxaudio/Object.py
glxaudio/RingBuffer.py
glxaudio/Sleep.py
glxaudio/__init__.py
glxaudio/file.py