Metadata-Version: 2.1
Name: galaxie-audio
Version: 0.1.5
Summary: Galaxie Audio is a height level wrapper for pyaudio with player, recorder, spectrogram, and more.
Home-page: https://gitlab.com/Tuuux/galaxie-audio
Author: Tuxa
Author-email: tuxa@rtnp.org
License: GPLv3+
Download-URL: https://pypi.org/project/galaxie-audio
Project-URL: Read the Docs, https://galaxie-audio.readthedocs.io
Project-URL: GitLab, https://gitlab.com/Tuuux/galaxie-audio
Keywords: Galaxie Audio library
Platform: UNKNOWN
Classifier: Development Status :: 3 - Alpha
Classifier: Environment :: Console
Classifier: Intended Audience :: Developers
Classifier: License :: OSI Approved :: GNU General Public License v3 or later (GPLv3+)
Classifier: Topic :: Software Development :: Libraries :: Python Modules
Classifier: Programming Language :: Python
Classifier: Programming Language :: Python :: 3 :: Only
License-File: LICENSE.rst
